EraCore/__init__.py
EraCore/Core.py
eracore-0.0.6.dist-info/METADATA
eracore-0.0.6.dist-info/WHEEL
eracore-0.0.6.dist-info/RECORD
