Metadata-Version: 2.1
Name: eracore
Version: 0.0.6
Summary: Core
License: MIT
Author: Eragod
Author-email: eragod1337@mail.ru
Requires-Python: >=3.11,<4.0
Classifier: License :: OSI Approved :: MIT License
Classifier: Programming Language :: Python :: 3
Classifier: Programming Language :: Python :: 3.11
